sd_sdk_python/__init__.py
sd_sdk_python/sd_sdk.py
sd_sdk_python/sd_sdk_wireless.py
sd_sdk_python-0.2.5.dist-info/LICENSE
sd_sdk_python-0.2.5.dist-info/METADATA
sd_sdk_python-0.2.5.dist-info/WHEEL
sd_sdk_python-0.2.5.dist-info/RECORD
